fake_data_generator/__init__.py
fake_data_generator/generate_fake_data.py
fake_data_generator-0.0.10.dist-info/METADATA
fake_data_generator-0.0.10.dist-info/WHEEL
fake_data_generator-0.0.10.dist-info/top_level.txt
fake_data_generator-0.0.10.dist-info/RECORD
