Metadata-Version: 2.1
Name: fake-data-generator
Version: 0.0.10
Summary: Fake Data generator
Home-page: UNKNOWN
Author: Sarang Manjrekar
Author-email: <manjrekar.sarang@email.com>
License: UNKNOWN
Keywords: python,fake data,dummy data
Platform: UNKNOWN
Classifier: Development Status :: 3 - Alpha
Classifier: Intended Audience :: Education
Classifier: Programming Language :: Python :: 3
Classifier: Operating System :: MacOS :: MacOS X
Classifier: Operating System :: Microsoft :: Windows
